.mailmap
AUTHORS.txt
CHANGELOG
LICENSE
MANIFEST.in
README.md
logo.jpeg
setup.py
docs/handler.md
docs/ocr.md
docs/pdf.md
src/py3office/__init__.py
src/py3office/handler.py
src/py3office/ocr.py
src/py3office/pdf.py
src/py3office.egg-info/PKG-INFO
src/py3office.egg-info/SOURCES.txt
src/py3office.egg-info/dependency_links.txt
src/py3office.egg-info/requires.txt
src/py3office.egg-info/top_level.txt