Metadata-Version: 2.1
Name: py3office
Version: 0.3.0
Summary: 提供python3版本的自动化办公常用处理方法
Home-page: https://github.com/zxl20070701/py3office
Author: zxl20070701
Author-email: 1904314465@qq.com
Maintainer: zxl20070701
Maintainer-email: 1904314465@qq.com
License: MIT
Keywords: pdf,office,python3
Classifier: Programming Language :: Python :: 3
Classifier: License :: OSI Approved :: MIT License
Classifier: Operating System :: OS Independent
License-File: LICENSE
License-File: AUTHORS.txt
